cordic_32bit_pipelined.v
`timescale 1ns / 1ps

module cordic_32bit_pipelined (
    input wire clk,
    input wire rst,
    input wire valid_in,
    input wire mode, // 0: Rotation (Sin/Cos), 1: Vectoring (ArcTan/Magnitude)
    input wire signed [31:0] x_in,
    input wire signed [31:0] y_in,
    input wire signed [31:0] z_in,
    output wire valid_out,
    output wire signed [31:0] x_out,
    output wire signed [31:0] y_out,
    output wire signed [31:0] z_out
);

    // CORDIC Angles Table (32-bit, representing degrees where 45 degrees = 2^29)
    // Z is mapped such that 180 degrees = 2^31. Range: [-180, +180)
    wire [31:0] atan_table [0:31];
    assign atan_table[0]  = 32'h20000000; // atan(2^0)  = 45.000 deg
    assign atan_table[1]  = 32'h12E4051E; // atan(2^-1) = 26.565 deg
    assign atan_table[2]  = 32'h09FB385B; // atan(2^-2) = 14.036 deg
    assign atan_table[3]  = 32'h051111D4; // atan(2^-3) = 7.125 deg
    assign atan_table[4]  = 32'h028B0D43; // atan(2^-4) = 3.576 deg
    assign atan_table[5]  = 32'h0145D7E1;
    assign atan_table[6]  = 32'h00A2F61E;
    assign atan_table[7]  = 32'h00517C55;
    assign atan_table[8]  = 32'h0028BE53;
    assign atan_table[9]  = 32'h00145F2E;
    assign atan_table[10] = 32'h000A2F98;
    assign atan_table[11] = 32'h000517CC;
    assign atan_table[12] = 32'h00028BE6;
    assign atan_table[13] = 32'h000145F3;
    assign atan_table[14] = 32'h0000A2FA;
    assign atan_table[15] = 32'h0000517D;
    assign atan_table[16] = 32'h000028BE;
    assign atan_table[17] = 32'h0000145F;
    assign atan_table[18] = 32'h00000A30;
    assign atan_table[19] = 32'h00000517;
    assign atan_table[20] = 32'h0000028B;
    assign atan_table[21] = 32'h00000145;
    assign atan_table[22] = 32'h000000A2;
    assign atan_table[23] = 32'h00000051;
    assign atan_table[24] = 32'h00000028;
    assign atan_table[25] = 32'h00000014;
    assign atan_table[26] = 32'h0000000A;
    assign atan_table[27] = 32'h00000005;
    assign atan_table[28] = 32'h00000002;
    assign atan_table[29] = 32'h00000001;
    assign atan_table[30] = 32'h00000001;
    assign atan_table[31] = 32'h00000000;

    // Pipeline registers for 33 stages (1 input stage + 32 cordic stages)
    reg signed [31:0] x [0:32];
    reg signed [31:0] y [0:32];
    reg signed [31:0] z [0:32];
    reg valid [0:32];
    reg mode_pipe [0:32];

    // Stage 0: Latch inputs
    always @(posedge clk) begin
        if (rst) begin
            valid[0]     <= 1'b0;
            mode_pipe[0] <= 1'b0;
            x[0]         <= 32'd0;
            y[0]         <= 32'd0;
            z[0]         <= 32'd0;
        end else begin
            valid[0]     <= valid_in;
            mode_pipe[0] <= mode;
            x[0]         <= x_in;
            y[0]         <= y_in;
            z[0]         <= z_in;
        end
    end

    // Stages 1 to 32: CORDIC Rotations
    genvar i;
    generate
        for (i = 0; i < 32; i = i + 1) begin : CORDIC_STAGES
            
            // Determine Rotation Direction 
            // Rotation (mode 0): Drive Z to 0. Vectoring (mode 1): Drive Y to 0.
            wire z_sign = z[i][31];
            wire y_sign = y[i][31];
            
            // d_dir == 1: Rotate CW (- angle), d_dir == 0: Rotate CCW (+ angle)
            wire d_dir = (mode_pipe[i] == 0) ? z_sign : ~y_sign; 
            
            // Arithmetic right shifts
            wire signed [31:0] x_shifted = x[i] >>> i;
            wire signed [31:0] y_shifted = y[i] >>> i;
            
            always @(posedge clk) begin
                if (rst) begin
                    valid[i+1]     <= 1'b0;
                    mode_pipe[i+1] <= 1'b0;
                    x[i+1]         <= 32'd0;
                    y[i+1]         <= 32'd0;
                    z[i+1]         <= 32'd0;
                end else begin
                    valid[i+1]     <= valid[i];
                    mode_pipe[i+1] <= mode_pipe[i];
                    
                    if (d_dir) begin
                        // Rotate CW
                        x[i+1] <= x[i] + y_shifted;
                        y[i+1] <= y[i] - x_shifted;
                        z[i+1] <= z[i] + atan_table[i];
                    end else begin
                        // Rotate CCW
                        x[i+1] <= x[i] - y_shifted;
                        y[i+1] <= y[i] + x_shifted;
                        z[i+1] <= z[i] - atan_table[i];
                    end
                end
            end
        end
    endgenerate

    // Final Outputs 
    // Data exhibits a 33 clock-cycle latency from valid_in to valid_out.
    assign valid_out = valid[32];
    assign x_out     = x[32];
    assign y_out     = y[32];
    assign z_out     = z[32];

endmodule

tb_cordic.v
`timescale 1ns / 1ps

module tb_cordic;

    reg clk;
    reg rst;
    reg valid_in;
    reg mode;
    reg signed [31:0] x_in;
    reg signed [31:0] y_in;
    reg signed [31:0] z_in;
    
    wire valid_out;
    wire signed [31:0] x_out;
    wire signed [31:0] y_out;
    wire signed [31:0] z_out;
    
    cordic_32bit_pipelined dut (
        .clk(clk),
        .rst(rst),
        .valid_in(valid_in),
        .mode(mode),
        .x_in(x_in),
        .y_in(y_in),
        .z_in(z_in),
        .valid_out(valid_out),
        .x_out(x_out),
        .y_out(y_out),
        .z_out(z_out)
    );
    
    // 100MHz clock
    always #5 clk = ~clk;
    
    initial begin
        $dumpfile("cordic_waves.vcd");
        $dumpvars(0, tb_cordic);
        
        clk = 0; rst = 1; valid_in = 0; mode = 0;
        x_in = 0; y_in = 0; z_in = 0;
        
        #25; 
        rst = 0; 
        
        // ---------------------------------------------------------
        // TEST CASE 1: ROTATION MODE (Target Angle = 30 degrees)
        // ---------------------------------------------------------
        @(posedge clk);
        #1; 
        valid_in = 1; 
        mode = 0; 
        x_in = 32'h26DD3B36; 
        y_in = 32'd0; 
        z_in = 32'h15555555; // 30 degrees
        
        // ---------------------------------------------------------
        // TEST CASE 2: VECTORING MODE (Target Y/X = 1/sqrt(3))
        // ---------------------------------------------------------
        @(posedge clk);
        #1; 
        valid_in = 1; 
        mode = 1;
        x_in = 32'h1BB67E31; // sqrt(3)
        y_in = 32'h10000000; // 1.0
        z_in = 32'd0;
        
        @(posedge clk);
        #1; 
        valid_in = 0;
        
        #1000;
        $finish; 
    end

    // ---------------------------------------------------------
    // ADVANCED TERMINAL MONITOR
    // ---------------------------------------------------------
    integer test_cnt = 0;
    real real_cos, real_sin, real_atan;

    always @(posedge clk) begin
        if (valid_out == 1'b1) begin
            test_cnt = test_cnt + 1;
            
            // Do the floating point conversions
            // Divide X and Y by 2^30 (1073741824.0)
            real_cos  = $itor(x_out) / 1073741824.0;
            real_sin  = $itor(y_out) / 1073741824.0;
            
            // Multiply Z by 45 and divide by 2^29 (536870912.0)
            real_atan = ($itor(z_out) * 45.0) / 536870912.0;

            $display("\n============================================================");
            $display(" TIME: %0t ns | TEST CASE %0d", $time, test_cnt);
            $display("------------------------------------------------------------");
            $display(" RAW (Hex)  | X_out: %h | Y_out: %h | Z_out: %h", x_out, y_out, z_out);
            
            if (test_cnt == 1) begin
                $display(" MODE       | ROTATION (Calculates Sine & Cosine)");
                $display(" TARGET     | Calculate Sin/Cos for Angle = 30.0 degrees");
                $display(" RESULT     | COSINE = %f", real_cos);
                $display(" RESULT     | SINE   = %f", real_sin);
            end else if (test_cnt == 2) begin
                $display(" MODE       | VECTORING (Calculates Arctangent)");
                $display(" TARGET     | Calculate Arctan of 1.0 / sqrt(3)");
                $display(" EXPECTED   | Angle should equal 30.0 degrees");
                $display(" RESULT     | ARCTAN = %f degrees", real_atan);
            end
            $display("============================================================\n");
        end
    end

endmodule

cordic_waves.vcd
$date
	Wed Aug 05 17:44:25 2026
$end
$version
	Icarus Verilog
$end
$timescale
	1ps
$end
$scope module tb_cordic $end
$var wire 32 ! z_out [31:0] $end
$var wire 32 " y_out [31:0] $end
$var wire 32 # x_out [31:0] $end
$var wire 1 $ valid_out $end
$var reg 1 % clk $end
$var reg 1 & mode $end
$var reg 1 ' rst $end
$var reg 1 ( valid_in $end
$var reg 32 ) x_in [31:0] $end
$var reg 32 * y_in [31:0] $end
$var reg 32 + z_in [31:0] $end
$var real 1 , real_atan $end
$var real 1 - real_cos $end
$var real 1 . real_sin $end
$var integer 32 / test_cnt [31:0] $end
$scope module dut $end
$var wire 1 % clk $end
$var wire 1 & mode $end
$var wire 1 ' rst $end
$var wire 1 ( valid_in $end
$var wire 1 $ valid_out $end
$var wire 32 0 x_in [31:0] $end
$var wire 32 1 x_out [31:0] $end
$var wire 32 2 y_in [31:0] $end
$var wire 32 3 y_out [31:0] $end
$var wire 32 4 z_in [31:0] $end
$var wire 32 5 z_out [31:0] $end
$scope begin CORDIC_STAGES[0] $end
$var wire 32 6 x_shifted [31:0] $end
$var wire 32 7 y_shifted [31:0] $end
$var wire 1 8 z_sign $end
$var wire 1 9 y_sign $end
$var wire 1 : d_dir $end
$var parameter 2 ; i $end
$upscope $end
$scope begin CORDIC_STAGES[1] $end
$var wire 1 < z_sign $end
$var wire 1 = y_sign $end
$var wire 32 > y_shifted [31:0] $end
$var wire 32 ? x_shifted [31:0] $end
$var wire 1 @ d_dir $end
$var parameter 2 A i $end
$upscope $end
$scope begin CORDIC_STAGES[2] $end
$var wire 1 B z_sign $end
$var wire 1 C y_sign $end
$var wire 32 D y_shifted [31:0] $end
$var wire 32 E x_shifted [31:0] $end
$var wire 1 F d_dir $end
$var parameter 3 G i $end
$upscope $end
$scope begin CORDIC_STAGES[3] $end
$var wire 1 H z_sign $end
$var wire 1 I y_sign $end
$var wire 32 J y_shifted [31:0] $end
$var wire 32 K x_shifted [31:0] $end
$var wire 1 L d_dir $end
$var parameter 3 M i $end
$upscope $end
$scope begin CORDIC_STAGES[4] $end
$var wire 1 N z_sign $end
$var wire 1 O y_sign $end
$var wire 32 P y_shifted [31:0] $end
$var wire 32 Q x_shifted [31:0] $end
$var wire 1 R d_dir $end
$var parameter 4 S i $end
$upscope $end
$scope begin CORDIC_STAGES[5] $end
$var wire 1 T z_sign $end
$var wire 1 U y_sign $end
$var wire 32 V y_shifted [31:0] $end
$var wire 32 W x_shifted [31:0] $end
$var wire 1 X d_dir $end
$var parameter 4 Y i $end
$upscope $end
$scope begin CORDIC_STAGES[6] $end
$var wire 1 Z z_sign $end
$var wire 1 [ y_sign $end
$var wire 32 \ y_shifted [31:0] $end
$var wire 32 ] x_shifted [31:0] $end
$var wire 1 ^ d_dir $end
$var parameter 4 _ i $end
$upscope $end
$scope begin CORDIC_STAGES[7] $end
$var wire 1 ` z_sign $end
$var wire 1 a y_sign $end
$var wire 32 b y_shifted [31:0] $end
$var wire 32 c x_shifted [31:0] $end
$var wire 1 d d_dir $end
$var parameter 4 e i $end
$upscope $end
$scope begin CORDIC_STAGES[8] $end
$var wire 1 f z_sign $end
$var wire 1 g y_sign $end
$var wire 32 h y_shifted [31:0] $end
$var wire 32 i x_shifted [31:0] $end
$var wire 1 j d_dir $end
$var parameter 5 k i $end
$upscope $end
$scope begin CORDIC_STAGES[9] $end
$var wire 1 l z_sign $end
$var wire 1 m y_sign $end
$var wire 32 n y_shifted [31:0] $end
$var wire 32 o x_shifted [31:0] $end
$var wire 1 p d_dir $end
$var parameter 5 q i $end
$upscope $end
$scope begin CORDIC_STAGES[10] $end
$var wire 1 r z_sign $end
$var wire 1 s y_sign $end
$var wire 32 t y_shifted [31:0] $end
$var wire 32 u x_shifted [31:0] $end
$var wire 1 v d_dir $end
$var parameter 5 w i $end
$upscope $end
$scope begin CORDIC_STAGES[11] $end
$var wire 1 x z_sign $end
$var wire 1 y y_sign $end
$var wire 32 z y_shifted [31:0] $end
$var wire 32 { x_shifted [31:0] $end
$var wire 1 | d_dir $end
$var parameter 5 } i $end
$upscope $end
$scope begin CORDIC_STAGES[12] $end
$var wire 1 ~ z_sign $end
$var wire 1 !" y_sign $end
$var wire 32 "" y_shifted [31:0] $end
$var wire 32 #" x_shifted [31:0] $end
$var wire 1 $" d_dir $end
$var parameter 5 %" i $end
$upscope $end
$scope begin CORDIC_STAGES[13] $end
$var wire 1 &" z_sign $end
$var wire 1 '" y_sign $end
$var wire 32 (" y_shifted [31:0] $end
$var wire 32 )" x_shifted [31:0] $end
$var wire 1 *" d_dir $end
$var parameter 5 +" i $end
$upscope $end
$scope begin CORDIC_STAGES[14] $end
$var wire 1 ," z_sign $end
$var wire 1 -" y_sign $end
$var wire 32 ." y_shifted [31:0] $end
$var wire 32 /" x_shifted [31:0] $end
$var wire 1 0" d_dir $end
$var parameter 5 1" i $end
$upscope $end
$scope begin CORDIC_STAGES[15] $end
$var wire 1 2" z_sign $end
$var wire 1 3" y_sign $end
$var wire 32 4" y_shifted [31:0] $end
$var wire 32 5" x_shifted [31:0] $end
$var wire 1 6" d_dir $end
$var parameter 5 7" i $end
$upscope $end
$scope begin CORDIC_STAGES[16] $end
$var wire 1 8" z_sign $end
$var wire 1 9" y_sign $end
$var wire 32 :" y_shifted [31:0] $end
$var wire 32 ;" x_shifted [31:0] $end
$var wire 1 <" d_dir $end
$var parameter 6 =" i $end
$upscope $end
$scope begin CORDIC_STAGES[17] $end
$var wire 1 >" z_sign $end
$var wire 1 ?" y_sign $end
$var wire 32 @" y_shifted [31:0] $end
$var wire 32 A" x_shifted [31:0] $end
$var wire 1 B" d_dir $end
$var parameter 6 C" i $end
$upscope $end
$scope begin CORDIC_STAGES[18] $end
$var wire 1 D" z_sign $end
$var wire 1 E" y_sign $end
$var wire 32 F" y_shifted [31:0] $end
$var wire 32 G" x_shifted [31:0] $end
$var wire 1 H" d_dir $end
$var parameter 6 I" i $end
$upscope $end
$scope begin CORDIC_STAGES[19] $end
$var wire 1 J" z_sign $end
$var wire 1 K" y_sign $end
$var wire 32 L" y_shifted [31:0] $end
$var wire 32 M" x_shifted [31:0] $end
$var wire 1 N" d_dir $end
$var parameter 6 O" i $end
$upscope $end
$scope begin CORDIC_STAGES[20] $end
$var wire 1 P" z_sign $end
$var wire 1 Q" y_sign $end
$var wire 32 R" y_shifted [31:0] $end
$var wire 32 S" x_shifted [31:0] $end
$var wire 1 T" d_dir $end
$var parameter 6 U" i $end
$upscope $end
$scope begin CORDIC_STAGES[21] $end
$var wire 1 V" z_sign $end
$var wire 1 W" y_sign $end
$var wire 32 X" y_shifted [31:0] $end
$var wire 32 Y" x_shifted [31:0] $end
$var wire 1 Z" d_dir $end
$var parameter 6 [" i $end
$upscope $end
$scope begin CORDIC_STAGES[22] $end
$var wire 1 \" z_sign $end
$var wire 1 ]" y_sign $end
$var wire 32 ^" y_shifted [31:0] $end
$var wire 32 _" x_shifted [31:0] $end
$var wire 1 `" d_dir $end
$var parameter 6 a" i $end
$upscope $end
$scope begin CORDIC_STAGES[23] $end
$var wire 1 b" z_sign $end
$var wire 1 c" y_sign $end
$var wire 32 d" y_shifted [31:0] $end
$var wire 32 e" x_shifted [31:0] $end
$var wire 1 f" d_dir $end
$var parameter 6 g" i $end
$upscope $end
$scope begin CORDIC_STAGES[24] $end
$var wire 1 h" z_sign $end
$var wire 1 i" y_sign $end
$var wire 32 j" y_shifted [31:0] $end
$var wire 32 k" x_shifted [31:0] $end
$var wire 1 l" d_dir $end
$var parameter 6 m" i $end
$upscope $end
$scope begin CORDIC_STAGES[25] $end
$var wire 1 n" z_sign $end
$var wire 1 o" y_sign $end
$var wire 32 p" y_shifted [31:0] $end
$var wire 32 q" x_shifted [31:0] $end
$var wire 1 r" d_dir $end
$var parameter 6 s" i $end
$upscope $end
$scope begin CORDIC_STAGES[26] $end
$var wire 1 t" z_sign $end
$var wire 1 u" y_sign $end
$var wire 32 v" y_shifted [31:0] $end
$var wire 32 w" x_shifted [31:0] $end
$var wire 1 x" d_dir $end
$var parameter 6 y" i $end
$upscope $end
$scope begin CORDIC_STAGES[27] $end
$var wire 1 z" z_sign $end
$var wire 1 {" y_sign $end
$var wire 32 |" y_shifted [31:0] $end
$var wire 32 }" x_shifted [31:0] $end
$var wire 1 ~" d_dir $end
$var parameter 6 !# i $end
$upscope $end
$scope begin CORDIC_STAGES[28] $end
$var wire 1 "# z_sign $end
$var wire 1 ## y_sign $end
$var wire 32 $# y_shifted [31:0] $end
$var wire 32 %# x_shifted [31:0] $end
$var wire 1 &# d_dir $end
$var parameter 6 '# i $end
$upscope $end
$scope begin CORDIC_STAGES[29] $end
$var wire 1 (# z_sign $end
$var wire 1 )# y_sign $end
$var wire 32 *# y_shifted [31:0] $end
$var wire 32 +# x_shifted [31:0] $end
$var wire 1 ,# d_dir $end
$var parameter 6 -# i $end
$upscope $end
$scope begin CORDIC_STAGES[30] $end
$var wire 1 .# z_sign $end
$var wire 1 /# y_sign $end
$var wire 32 0# y_shifted [31:0] $end
$var wire 32 1# x_shifted [31:0] $end
$var wire 1 2# d_dir $end
$var parameter 6 3# i $end
$upscope $end
$scope begin CORDIC_STAGES[31] $end
$var wire 1 4# z_sign $end
$var wire 1 5# y_sign $end
$var wire 32 6# y_shifted [31:0] $end
$var wire 32 7# x_shifted [31:0] $end
$var wire 1 8# d_dir $end
$var parameter 6 9# i $end
$upscope $end
$upscope $end
$upscope $end
$enddefinitions $end
$comment Show the parameter values. $end
$dumpall
b11111 9#
b11110 3#
b11101 -#
b11100 '#
b11011 !#
b11010 y"
b11001 s"
b11000 m"
b10111 g"
b10110 a"
b10101 ["
b10100 U"
b10011 O"
b10010 I"
b10001 C"
b10000 ="
b1111 7"
b1110 1"
b1101 +"
b1100 %"
b1011 }
b1010 w
b1001 q
b1000 k
b111 e
b110 _
b101 Y
b100 S
b11 M
b10 G
b1 A
b0 ;
$end
#0
$dumpvars
x8#
bx 7#
bx 6#
x5#
x4#
x2#
bx 1#
bx 0#
x/#
x.#
x,#
bx +#
bx *#
x)#
x(#
x&#
bx %#
bx $#
x##
x"#
x~"
bx }"
bx |"
x{"
xz"
xx"
bx w"
bx v"
xu"
xt"
xr"
bx q"
bx p"
xo"
xn"
xl"
bx k"
bx j"
xi"
xh"
xf"
bx e"
bx d"
xc"
xb"
x`"
bx _"
bx ^"
x]"
x\"
xZ"
bx Y"
bx X"
xW"
xV"
xT"
bx S"
bx R"
xQ"
xP"
xN"
bx M"
bx L"
xK"
xJ"
xH"
bx G"
bx F"
xE"
xD"
xB"
bx A"
bx @"
x?"
x>"
x<"
bx ;"
bx :"
x9"
x8"
x6"
bx 5"
bx 4"
x3"
x2"
x0"
bx /"
bx ."
x-"
x,"
x*"
bx )"
bx ("
x'"
x&"
x$"
bx #"
bx ""
x!"
x~
x|
bx {
bx z
xy
xx
xv
bx u
bx t
xs
xr
xp
bx o
bx n
xm
xl
xj
bx i
bx h
xg
xf
xd
bx c
bx b
xa
x`
x^
bx ]
bx \
x[
xZ
xX
bx W
bx V
xU
xT
xR
bx Q
bx P
xO
xN
xL
bx K
bx J
xI
xH
xF
bx E
bx D
xC
xB
x@
bx ?
bx >
x=
x<
x:
x9
x8
bx 7
bx 6
bx 5
b0 4
bx 3
b0 2
bx 1
b0 0
b0 /
r0 .
r0 -
r0 ,
b0 +
b0 *
b0 )
0(
1'
0&
0%
x$
bx #
bx "
bx !
$end
#5000
0@
0F
0L
0R
0X
0^
0d
0j
0p
0v
0|
0$"
0*"
00"
06"
0<"
0B"
0H"
0N"
0T"
0Z"
0`"
0f"
0l"
0r"
0x"
0~"
0&#
0,#
02#
08#
0:
0<
0=
b0 >
b0 ?
0B
0C
b0 D
b0 E
0H
0I
b0 J
b0 K
0N
0O
b0 P
b0 Q
0T
0U
b0 V
b0 W
0Z
0[
b0 \
b0 ]
0`
0a
b0 b
b0 c
0f
0g
b0 h
b0 i
0l
0m
b0 n
b0 o
0r
0s
b0 t
b0 u
0x
0y
b0 z
b0 {
0~
0!"
b0 ""
b0 #"
0&"
0'"
b0 ("
b0 )"
0,"
0-"
b0 ."
b0 /"
02"
03"
b0 4"
b0 5"
08"
09"
b0 :"
b0 ;"
0>"
0?"
b0 @"
b0 A"
0D"
0E"
b0 F"
b0 G"
0J"
0K"
b0 L"
b0 M"
0P"
0Q"
b0 R"
b0 S"
0V"
0W"
b0 X"
b0 Y"
0\"
0]"
b0 ^"
b0 _"
0b"
0c"
b0 d"
b0 e"
0h"
0i"
b0 j"
b0 k"
0n"
0o"
b0 p"
b0 q"
0t"
0u"
b0 v"
b0 w"
0z"
0{"
b0 |"
b0 }"
0"#
0##
b0 $#
b0 %#
0(#
0)#
b0 *#
b0 +#
0.#
0/#
b0 0#
b0 1#
04#
05#
b0 6#
b0 7#
08
09
b0 !
b0 5
b0 "
b0 3
b0 #
b0 1
0$
b0 7
b0 6
1%
#10000
0%
#15000
1%
#20000
0%
#25000
1@
1F
1L
1R
1X
1^
1d
1j
1p
1v
1|
1$"
1*"
10"
16"
1<"
1B"
1H"
1N"
1T"
1Z"
1`"
1f"
1l"
1r"
1x"
1~"
1&#
1,#
12#
18#
1<
1B
1H
1N
1T
1Z
1`
1f
1l
1r
1x
1~
1&"
1,"
12"
18"
1>"
1D"
1J"
1P"
1V"
1\"
1b"
1h"
1n"
1t"
1z"
1"#
1(#
1.#
14#
1%
0'
#26000
b10101010101010101010101010101 +
b10101010101010101010101010101 4
b100110110111010011101100110110 )
b100110110111010011101100110110 0
1(
#30000
0%
#35000
08#
04#
b100110110111010011101100110110 6
b11111111111111111111111111111111 !
b11111111111111111111111111111111 5
1%
#36000
b0 +
b0 4
b10000000000000000000000000000 *
b10000000000000000000000000000 2
b11011101101100111111000110001 )
b11011101101100111111000110001 0
1&
#40000
0%
#45000
b10011011011101001110110011011 >
b10011011011101001110110011011 ?
1:
b0 !
b0 5
b10000000000000000000000000000 7
b11011101101100111111000110001 6
1%
#46000
0(
#50000
0%
#55000
0@
18#
0R
0F
14#
0N
0B
b100110110111010011101100110 D
b1110100100101111011000110100 E
0<
1=
b11111010001001001100000011100111 >
b10101110110110011111100011000 ?
1%
#60000
0%
#65000
b10100010010011000000111001 D
b1100011001000110111101010010 E
1F
b100010000000011001001111001 J
b110101011100000011000101101 K
b11111111111111111111111111111111 !
b11111111111111111111111111111111 5
1%
#70000
0%
#75000
0L
0d
0^
0`
0Z
b1101101010011100011011010 P
b11100110110000011000111110 Q
0H
1I
b11111111101110000000101000110010 J
b110100000110101110110110000 K
1%
#80000
0%
#85000
0X
0j
0p
b10001000011101011110100 P
b11010001100010111000110101 Q
1R
0T
b111101110111010010011111 V
b1101111111101100101011000 W
0f
0l
1%
#90000
0%
#95000
1j
1^
1f
1Z
b100000101011100110110100 \
b110111000000111011011001 ]
b1111110110000001000 V
b1101001010011100011110010 W
1X
1%
#100000
0%
#105000
0^
1p
0v
0$"
0Z
1[
b11111111111111010110000100100000 \
b110100101011110000101001 ]
b1111111010010010111100 b
b11011110000110011100000 c
1l
0r
0~
b11111111111111111111111111111110 !
b11111111111111111111111111111110 5
1%
#110000
0%
#115000
1$"
0|
1v
1~
0x
1r
b1000000100000101101011 h
b1101110100011011001011 i
b101011000001000 b
b11010010110001101010010 c
1d
1%
#120000
0%
#125000
0j
1|
0*"
06"
0f
1g
b11111111111111111100000110100000 h
b1101001011000111111111 i
b100000000010100010010 n
b110111011001110000110 o
1x
0&"
02"
b11111111111111111111111111111101 !
b11111111111111111111111111111101 5
1%
#130000
0%
#135000
0p
00"
0$"
0v
0,"
0~
0r
b1111111101110011100 t
b11011101110111000100 u
0l
1m
b11111111111111111111101100101001 n
b110100101100100011110 o
b11111111111111111111111111111100 !
b11111111111111111111111111111100 5
1%
#140000
0%
#145000
0|
10"
16"
0H"
b10000101011 t
b11010010110010010000 u
1v
0x
b111111111110001001 z
b1101110110111100010 {
1,"
12"
0D"
b11111111111111111111111111111011 !
b11111111111111111111111111111011 5
1%
#150000
0%
#155000
06"
1$"
02"
1~
b100000000000110011 ""
b110111011010110001 #"
b1101111 z
b1101001011001001000 {
1|
b11111111111111111111111111111001 !
b11111111111111111111111111111001 5
1%
#160000
0%
#165000
0$"
16"
1H"
0Z"
0~
1!"
b11111111111111111111111111001110 ""
b110100101100100100 #"
b1111111111111110 ("
b11011101101101000 )"
12"
1D"
0V"
b11111111111111111111111111111010 !
b11111111111111111111111111111010 5
1%
#170000
0%
#175000
0H"
0<"
0D"
08"
b1000000000000110 ."
b1101110110110000 /"
b1 ("
b11010010110010010 )"
1*"
1%
#180000
0%
#185000
00"
0B"
0T"
1Z"
0l"
0,"
1-"
b11111111111111111111111111111010 ."
b1101001011001001 /"
b100000000000001 4"
b110111011011001 5"
0>"
0P"
1V"
0h"
b11111111111111111111111111111001 !
b11111111111111111111111111111001 5
1%
#190000
0%
#195000
06"
0`"
0Z"
0N"
1H"
1<"
0\"
0V"
0J"
1D"
18"
b10000000000000 :"
b11011101101100 ;"
02"
13"
b11111111111111111111111111111110 4"
b110100101100100 5"
1%
#200000
0%
#205000
0<"
1N"
1`"
0f"
08"
19"
b11111111111111111111111111111111 :"
b11010010110010 ;"
b111111111111 @"
b1101110110110 A"
1J"
1\"
0b"
b11111111111111111111111111111010 !
b11111111111111111111111111111010 5
1%
#210000
0%
#215000
0&#
1f"
0`"
0"#
1b"
0\"
b100000000000 F"
b110111011011 G"
1?"
b11111111111111111111111111111111 @"
b1101001011001 A"
0B"
1%
#220000
0%
#225000
1Z"
1l"
0r"
0D"
b0 F"
b110100101100 G"
b10000000000 L"
b11011101101 M"
1V"
1h"
0n"
1%
#230000
0%
#235000
02#
0,#
1r"
1`"
1T"
0.#
0(#
1n"
1\"
1P"
b1000000000 R"
b1101110110 S"
0J"
b0 L"
b11010010110 M"
1%
#240000
0%
#245000
0f"
0l"
0r"
1&#
12#
0P"
b0 R"
b1101001011 S"
b100000000 X"
b110111011 Y"
0b"
0h"
0n"
1"#
1.#
b11111111111111111111111111111100 !
b11111111111111111111111111111100 5
1%
#250000
0%
#255000
08#
02#
0&#
0x"
0`"
04#
0.#
0"#
0t"
0\"
b1111111 ^"
b11011101 _"
0V"
b0 X"
b110100101 Y"
b11111111111111111111111111111111 !
b11111111111111111111111111111111 5
1%
#260000
0%
#265000
1f"
1,#
b0 ^"
b11010010 _"
1`"
1b"
b111111 d"
b1101110 e"
1(#
b0 !
b0 5
1%
#270000
0%
#275000
18#
12#
0,#
1x"
14#
1.#
0(#
1t"
b11111 j"
b110111 k"
0b"
b0 d"
b1101001 e"
1%
#280000
0%
#285000
1&#
1,#
02#
08#
b0 j"
b110100 k"
1l"
b1111 p"
b11011 q"
1"#
1(#
0.#
04#
b11111111111111111111111111111111 !
b11111111111111111111111111111111 5
1%
#290000
0%
#295000
0&#
0x"
0"#
0t"
b111 v"
b1101 w"
1o"
b11111111111111111111111111111111 p"
b11010 q"
0r"
b0 !
b0 5
1%
#300000
0%
#305000
0,#
18#
1u"
b11111111111111111111111111111111 v"
0x"
b11 |"
b110 }"
0(#
14#
1%
#310000
0%
#315000
1&#
1"#
b1 $#
b11 %#
0z"
b0 |"
b11111111111111111111111111111111 !
b11111111111111111111111111111111 5
1%
#320000
0%
#325000
1,#
0"#
b0 $#
1(#
b1 +#
1%
#330000
0%
#335000
12#
1.#
0(#
1%
#340000
0%
#345000
08#
0.#
04#
1%
#350000
0%
#355000
18#
b0 !
b0 5
b11111111111111111111111010111 "
b11111111111111111111111010111 3
b110111011011001111010110000111 #
b110111011011001111010110000111 1
1$
1%
#360000
0%
#365000
b10101010101010101001100111101 !
b10101010101010101001100111101 5
b0 "
b0 3
b110100101100100100011101000101 #
b110100101100100100011101000101 1
r0.4999999618157744 .
r0.8660253351554275 -
b1 /
1%
#370000
0%
#375000
0$
r29.99995504505932 ,
r0 .
r0.8233812497928739 -
b10 /
1%
